ailink.py
AILink-0.0.7.dist-info/LICENSE
AILink-0.0.7.dist-info/METADATA
AILink-0.0.7.dist-info/WHEEL
AILink-0.0.7.dist-info/top_level.txt
AILink-0.0.7.dist-info/RECORD
