Metadata-Version: 2.1
Name: AILink
Version: 0.0.7
Summary: A creative idea involves wrapping the OpenAI library to facilitate seamless connections with domestic large models. This project emerged precisely because large model interfaces are compatible with OpenAI, making it easier to utilize large models compared to traditional methods.
Home-page: https://github.com/cador/AILink
Author: Haolin You
Author-email: cador.ai@aliyun.com
Requires-Python: >=3.10
License-File: LICENSE
Requires-Dist: openai (>=1.58.1)
Requires-Dist: httpx[socks] (>=0.28.1)
